setup.py
docs/HISTORY.txt
docs/INSTALL.txt
docs/LICENSE.GPL
docs/LICENSE.txt
openc/__init__.py
openc.excludesearch.egg-info/PKG-INFO
openc.excludesearch.egg-info/SOURCES.txt
openc.excludesearch.egg-info/dependency_links.txt
openc.excludesearch.egg-info/entry_points.txt
openc.excludesearch.egg-info/namespace_packages.txt
openc.excludesearch.egg-info/not-zip-safe
openc.excludesearch.egg-info/requires.txt
openc.excludesearch.egg-info/top_level.txt
openc/excludesearch/README.txt
openc/excludesearch/__init__.py
openc/excludesearch/adapters.py
openc/excludesearch/configure.zcml
openc/excludesearch/interfaces.py
openc/excludesearch/tests.py
openc/excludesearch/profiles/default/metadata.xml
openc/excludesearch/profiles/default/skins.xml
openc/excludesearch/skins/excludesearch_scripts/queryCatalog.py
