Metadata-Version: 1.0
Name: openc.excludesearch
Version: 0.1.1
Summary: Excludes a subtree from search.
Home-page: http://svn.plone.org/svn/plone/plone.example
Author: Matthew Wilkes
Author-email: matthew@matthewwilkes.co.uk
License: GPL
Platform: UNKNOWN
Classifier: Framework :: Plone
Classifier: Programming Language :: Python
Classifier: Topic :: Software Development :: Libraries :: Python Modules
